mkdocs_version_warning/__init__.py
readthedocs_version_warning_mkdocs_plugin-0.0.1.dist-info/LICENSE
readthedocs_version_warning_mkdocs_plugin-0.0.1.dist-info/METADATA
readthedocs_version_warning_mkdocs_plugin-0.0.1.dist-info/WHEEL
readthedocs_version_warning_mkdocs_plugin-0.0.1.dist-info/entry_points.txt
readthedocs_version_warning_mkdocs_plugin-0.0.1.dist-info/top_level.txt
readthedocs_version_warning_mkdocs_plugin-0.0.1.dist-info/RECORD
