Metadata-Version: 2.1
Name: readthedocs-version-warning-mkdocs-plugin
Version: 0.0.1
Summary: ReadTheDocs version warning MkDocs plugin replace placeholder text with warning banner for specific versions if deployed on Readthedocs
Home-page: https://github.com/grossmannmartin/readthedocs-version-warning-mkdocs-plugin
Author: Martin Grossmann
Author-email: martin@vyvoj.net
License: MIT
Platform: UNKNOWN
Requires-Dist: mkdocs
Requires-Dist: requests
